<?xml version="1.0" encoding="UTF-8"?>
<!DOCTYPE plist PUBLIC "-//Apple//DTD PLIST 1.0//EN" "http://www.apple.com/DTDs/PropertyList-1.0.dtd"/>

<plist version="1.0">
    <dict>
        <key>ROOT</key>
        <array>
            <dict>
                <key>id</key>
                <string>225</string>
                <key>className</key>
                <string>PTModelObjectImage</string>
                <key>Name</key>
                <dict>
                    <key>value</key>
                    <string>Untitled</string>
                </dict>
                <key>zDepth</key>
                <string>0</string>
            </dict>
            <dict>
                <key>id</key>
                <string>273</string>
                <key>className</key>
                <string>PTModelObjectImage</string>
                <key>Name</key>
                <dict>
                    <key>value</key>
                    <string>Untitled</string>
                </dict>
                <key>zDepth</key>
                <string>0</string>
            </dict>
            <dict>
                <key>id</key>
                <string>298</string>
                <key>className</key>
                <string>PTModelObjectImage</string>
                <key>Name</key>
                <dict>
                    <key>value</key>
                    <string>Untitled</string>
                </dict>
                <key>zDepth</key>
                <string>0</string>
            </dict>
            <dict>
                <key>id</key>
                <string>326</string>
                <key>className</key>
                <string>PTModelObjectImage</string>
                <key>Name</key>
                <dict>
                    <key>value</key>
                    <string>Untitled</string>
                </dict>
                <key>zDepth</key>
                <string>0</string>
            </dict>
            <dict>
                <key>id</key>
                <string>429</string>
                <key>className</key>
                <string>PTModelObjectImage</string>
                <key>Name</key>
                <dict>
                    <key>value</key>
                    <string>Untitled</string>
                </dict>
                <key>zDepth</key>
                <string>0</string>
            </dict>
            <dict>
                <key>id</key>
                <string>440</string>
                <key>className</key>
                <string>PTModelObjectImage</string>
                <key>Name</key>
                <dict>
                    <key>value</key>
                    <string>Untitled</string>
                </dict>
                <key>zDepth</key>
                <string>0</string>
            </dict>
            <dict>
                <key>id</key>
                <string>604</string>
                <key>className</key>
                <string>PTModelObjectImage</string>
                <key>Name</key>
                <dict>
                    <key>value</key>
                    <string>Untitled</string>
                </dict>
                <key>zDepth</key>
                <string>0</string>
            </dict>
            <dict>
                <key>id</key>
                <string>1944</string>
                <key>className</key>
                <string>PTModelObjectImage</string>
                <key>Name</key>
                <dict>
                    <key>value</key>
                    <string>Untitled</string>
                </dict>
                <key>zDepth</key>
                <string>0</string>
            </dict>
            <dict>
                <key>id</key>
                <string>3084</string>
                <key>className</key>
                <string>PTModelObjectImage</string>
                <key>Name</key>
                <dict>
                    <key>value</key>
                    <string>Untitled</string>
                </dict>
                <key>zDepth</key>
                <string>0</string>
            </dict>
            <dict>
                <key>id</key>
                <string>3095</string>
                <key>className</key>
                <string>PTModelObjectImage</string>
                <key>Name</key>
                <dict>
                    <key>value</key>
                    <string>Untitled</string>
                </dict>
                <key>zDepth</key>
                <string>0</string>
            </dict>
            <dict>
                <key>id</key>
                <string>3125</string>
                <key>className</key>
                <string>PTModelObjectImage</string>
                <key>Name</key>
                <dict>
                    <key>value</key>
                    <string>LabelStartText</string>
                </dict>
                <key>Position</key>
                <dict>
                    <key>value</key>
                    <string>{320.000,911.526}</string>
                    <key>useDefault</key>
                    <string>0</string>
                </dict>
                <key>zDepth</key>
                <string>3</string>
            </dict>
            <dict>
                <key>id</key>
                <string>3146</string>
                <key>className</key>
                <string>PTModelObjectImage</string>
                <key>Name</key>
                <dict>
                    <key>value</key>
                    <string>GameOverImage</string>
                </dict>
                <key>Position</key>
                <dict>
                    <key>value</key>
                    <string>{320.000,1009.677}</string>
                    <key>useDefault</key>
                    <string>0</string>
                </dict>
                <key>zDepth</key>
                <string>1</string>
            </dict>
            <dict>
                <key>id</key>
                <string>3168</string>
                <key>className</key>
                <string>PTModelObjectImage</string>
                <key>Name</key>
                <dict>
                    <key>value</key>
                    <string>MoveButton</string>
                </dict>
                <key>Position</key>
                <dict>
                    <key>value</key>
                    <string>{130.970,253.555}</string>
                    <key>useDefault</key>
                    <string>0</string>
                </dict>
                <key>Scale</key>
                <dict>
                    <key>value</key>
                    <string>{2.000,2.000}</string>
                    <key>useDefault</key>
                    <string>0</string>
                </dict>
                <key>Autohide</key>
                <dict>
                    <key>value</key>
                    <string>3.000000</string>
                    <key>useDefault</key>
                    <string>0</string>
                </dict>
                <key>zDepth</key>
                <string>3</string>
            </dict>
            <dict>
                <key>id</key>
                <string>3173</string>
                <key>className</key>
                <string>PTModelObjectImage</string>
                <key>Name</key>
                <dict>
                    <key>value</key>
                    <string>MoveButton</string>
                </dict>
                <key>Position</key>
                <dict>
                    <key>value</key>
                    <string>{517.528,253.555}</string>
                    <key>useDefault</key>
                    <string>0</string>
                </dict>
                <key>Rotation</key>
                <dict>
                    <key>value</key>
                    <string>180.000000</string>
                    <key>useDefault</key>
                    <string>0</string>
                </dict>
                <key>Scale</key>
                <dict>
                    <key>value</key>
                    <string>{2.000,2.000}</string>
                    <key>useDefault</key>
                    <string>0</string>
                </dict>
                <key>Autohide</key>
                <dict>
                    <key>value</key>
                    <string>3.000000</string>
                    <key>useDefault</key>
                    <string>0</string>
                </dict>
                <key>zDepth</key>
                <string>4</string>
            </dict>
            <dict>
                <key>id</key>
                <string>3209</string>
                <key>className</key>
                <string>PTModelObjectImage</string>
                <key>Name</key>
                <dict>
                    <key>value</key>
                    <string>Untitled</string>
                </dict>
                <key>zDepth</key>
                <string>0</string>
            </dict>
            <dict>
                <key>id</key>
                <string>3407</string>
                <key>className</key>
                <string>PTModelObjectImage</string>
                <key>Name</key>
                <dict>
                    <key>value</key>
                    <string>PauseText</string>
                </dict>
                <key>Position</key>
                <dict>
                    <key>value</key>
                    <string>{320.000,991.501}</string>
                    <key>useDefault</key>
                    <string>0</string>
                </dict>
                <key>zDepth</key>
                <string>1</string>
            </dict>
            <dict>
                <key>id</key>
                <string>3432</string>
                <key>className</key>
                <string>PTModelObjectImage</string>
                <key>Name</key>
                <dict>
                    <key>value</key>
                    <string>PauseBackground</string>
                </dict>
                <key>Position</key>
                <dict>
                    <key>value</key>
                    <string>{320.000,568.000}</string>
                    <key>useDefault</key>
                    <string>0</string>
                </dict>
                <key>Scale</key>
                <dict>
                    <key>value</key>
                    <string>{3.304,5.794}</string>
                    <key>useDefault</key>
                    <string>0</string>
                </dict>
                <key>zDepth</key>
                <string>0</string>
            </dict>
            <dict>
                <key>id</key>
                <string>3445</string>
                <key>className</key>
                <string>PTModelObjectImage</string>
                <key>Name</key>
                <dict>
                    <key>value</key>
                    <string>SplashBackground</string>
                </dict>
                <key>Position</key>
                <dict>
                    <key>value</key>
                    <string>{320.000,562.448}</string>
                    <key>useDefault</key>
                    <string>0</string>
                </dict>
                <key>Scale</key>
                <dict>
                    <key>value</key>
                    <string>{3.308,5.922}</string>
                    <key>useDefault</key>
                    <string>0</string>
                </dict>
                <key>zDepth</key>
                <string>0</string>
            </dict>
            <dict>
                <key>id</key>
                <string>3458</string>
                <key>className</key>
                <string>PTModelObjectImage</string>
                <key>Name</key>
                <dict>
                    <key>value</key>
                    <string>MainMenuBackgrond</string>
                </dict>
                <key>Position</key>
                <dict>
                    <key>value</key>
                    <string>{316.365,573.453}</string>
                    <key>useDefault</key>
                    <string>0</string>
                </dict>
                <key>Scale</key>
                <dict>
                    <key>value</key>
                    <string>{3.399,5.835}</string>
                    <key>useDefault</key>
                    <string>0</string>
                </dict>
                <key>zDepth</key>
                <string>0</string>
            </dict>
            <dict>
                <key>id</key>
                <string>3495</string>
                <key>className</key>
                <string>PTModelObjectImage</string>
                <key>Name</key>
                <dict>
                    <key>value</key>
                    <string>GameOverBackground</string>
                </dict>
                <key>Position</key>
                <dict>
                    <key>value</key>
                    <string>{320.000,568.000}</string>
                    <key>useDefault</key>
                    <string>0</string>
                </dict>
                <key>Scale</key>
                <dict>
                    <key>value</key>
                    <string>{3.381,5.853}</string>
                    <key>useDefault</key>
                    <string>0</string>
                </dict>
                <key>zDepth</key>
                <string>0</string>
            </dict>
            <dict>
                <key>id</key>
                <string>3574</string>
                <key>className</key>
                <string>PTModelObjectImage</string>
                <key>Name</key>
                <dict>
                    <key>value</key>
                    <string>BestText</string>
                </dict>
                <key>Position</key>
                <dict>
                    <key>value</key>
                    <string>{114.655,1080.486}</string>
                    <key>useDefault</key>
                    <string>0</string>
                </dict>
                <key>Scale</key>
                <dict>
                    <key>value</key>
                    <string>{0.619,0.619}</string>
                    <key>useDefault</key>
                    <string>0</string>
                </dict>
                <key>zDepth</key>
                <string>2</string>
            </dict>
            <dict>
                <key>id</key>
                <string>3693</string>
                <key>className</key>
                <string>PTModelObjectImage</string>
                <key>Name</key>
                <dict>
                    <key>value</key>
                    <string>Untitled</string>
                </dict>
                <key>zDepth</key>
                <string>0</string>
            </dict>
            <dict>
                <key>id</key>
                <string>4963</string>
                <key>className</key>
                <string>PTModelObjectImage</string>
                <key>Name</key>
                <dict>
                    <key>value</key>
                    <string>Untitled</string>
                </dict>
                <key>zDepth</key>
                <string>0</string>
            </dict>
            <dict>
                <key>id</key>
                <string>5351</string>
                <key>className</key>
                <string>PTModelObjectImage</string>
                <key>Name</key>
                <dict>
                    <key>value</key>
                    <string>LogoSplash</string>
                </dict>
                <key>Position</key>
                <dict>
                    <key>value</key>
                    <string>{321.818,586.176}</string>
                    <key>useDefault</key>
                    <string>0</string>
                </dict>
                <key>zDepth</key>
                <string>1</string>
            </dict>
        </array>
    </dict>
</plist>
